mlqa/__init__.py
mlqa/checkers.py
mlqa/identifiers.py
tests/__init__.py
tests/test_checkers.py
tests/test_identifier.py
mlqa-0.1.1.dist-info/LICENSE
mlqa-0.1.1.dist-info/METADATA
mlqa-0.1.1.dist-info/WHEEL
mlqa-0.1.1.dist-info/top_level.txt
mlqa-0.1.1.dist-info/RECORD
