Metadata-Version: 2.1
Name: mlqa
Version: 0.1.1
Summary: A Package to perform QA on data flows for Machine Learning.
Home-page: https://github.com/ddaskan/mlqa
Author: Dogan Askan
Author-email: doganaskan@gmail.com
License: MIT
Download-URL: https://pypi.python.org/pypi/mlqa
Project-URL: Bug Tracker, https://github.com/ddaskan/mlqa/issues
Project-URL: Documentation, https://mlqa.readthedocs.io/
Project-URL: Source Code, https://github.com/ddaskan/mlqa
Keywords: qa ml ai data analysis machine learning quality assurance
Platform: UNKNOWN
Classifier: Programming Language :: Python :: 3
Classifier: License :: OSI Approved :: MIT License
Classifier: Operating System :: OS Independent
Classifier: Topic :: Scientific/Engineering
Classifier: Topic :: Scientific/Engineering :: Artificial Intelligence
Classifier: Topic :: Software Development
Requires-Python: >=3.6
Requires-Dist: numpy (>=1.19.4)
Requires-Dist: pandas (>=1.1.5)
